[{"model": "translator.model_language_en", "pk": 9, "fields": {"value": "Append new recommended product"}}, {"model": "translator.model_language_en", "pk": 10, "fields": {"value": "First recommended product must exist in list product. To add recommended product you have to search product and click `Recommend` button in product details."}}, {"model": "translator.model_language_en", "pk": 11, "fields": {"value": "Price in {0} have to be greater than zero."}}, {"model": "translator.model_language_en", "pk": 12, "fields": {"value": "Stock have to be greater than zero."}}, {"model": "translator.model_language_en", "pk": 15, "fields": {"value": "Product's brand name is required."}}, {"model": "translator.model_language_en", "pk": 17, "fields": {"value": "Product's image is required."}}, {"model": "translator.model_language_en", "pk": 18, "fields": {"value": "Keywords"}}, {"model": "translator.model_language_en", "pk": 19, "fields": {"value": "Name"}}, {"model": "translator.model_language_en", "pk": 20, "fields": {"value": "Description"}}, {"model": "translator.model_language_en", "pk": 23, "fields": {"value": "Sign in"}}, {"model": "translator.model_language_en", "pk": 24, "fields": {"value": "Sign out"}}, {"model": "translator.model_language_en", "pk": 25, "fields": {"value": "Company details"}}, {"model": "translator.model_language_en", "pk": 26, "fields": {"value": "Map references"}}, {"model": "translator.model_language_en", "pk": 27, "fields": {"value": "Users' payments"}}, {"model": "translator.model_language_en", "pk": 28, "fields": {"value": "Root does not exist."}}, {"model": "translator.model_language_en", "pk": 29, "fields": {"value": "Wrong password."}}, {"model": "translator.model_language_en", "pk": 30, "fields": {"value": "Wrong password. Try again."}}, {"model": "translator.model_language_en", "pk": 31, "fields": {"value": "Password"}}, {"model": "translator.model_language_en", "pk": 32, "fields": {"value": "Change your password."}}, {"model": "translator.model_language_en", "pk": 33, "fields": {"value": "Confirm your new account."}}, {"model": "translator.model_language_en", "pk": 34, "fields": {"value": "Your order is confirmed."}}, {"model": "translator.model_language_en", "pk": 35, "fields": {"value": "Sign in"}}, {"model": "translator.model_language_en", "pk": 36, "fields": {"value": "Sign up"}}, {"model": "translator.model_language_en", "pk": 37, "fields": {"value": "Sign out"}}, {"model": "translator.model_language_en", "pk": 38, "fields": {"value": "Account"}}, {"model": "translator.model_language_en", "pk": 39, "fields": {"value": "Email"}}, {"model": "translator.model_language_en", "pk": 40, "fields": {"value": "Password"}}, {"model": "translator.model_language_en", "pk": 41, "fields": {"value": "User with this email does not exist."}}, {"model": "translator.model_language_en", "pk": 42, "fields": {"value": "Your account is not confirmed. Check your mailbox."}}, {"model": "translator.model_language_en", "pk": 43, "fields": {"value": "Wrong password. Try again."}}, {"model": "translator.model_language_en", "pk": 44, "fields": {"value": "Username"}}, {"model": "translator.model_language_en", "pk": 45, "fields": {"value": "Password"}}, {"model": "translator.model_language_en", "pk": 46, "fields": {"value": "Email"}}, {"model": "translator.model_language_en", "pk": 48, "fields": {"value": "Address Line"}}, {"model": "translator.model_language_en", "pk": 50, "fields": {"value": "City"}}, {"model": "translator.model_language_en", "pk": 51, "fields": {"value": "State / Province / Region"}}, {"model": "translator.model_language_en", "pk": 52, "fields": {"value": "ZIP / Postal Code"}}, {"model": "translator.model_language_en", "pk": 53, "fields": {"value": "Country"}}, {"model": "translator.model_language_en", "pk": 54, "fields": {"value": "User with this email does not exist."}}, {"model": "translator.model_language_en", "pk": 55, "fields": {"value": "Your account is not confirmed. Check your mailbox."}}, {"model": "translator.model_language_en", "pk": 56, "fields": {"value": "Email"}}, {"model": "translator.model_language_en", "pk": 57, "fields": {"value": "Password"}}, {"model": "translator.model_language_en", "pk": 58, "fields": {"value": "Account details"}}, {"model": "translator.model_language_en", "pk": 59, "fields": {"value": "Your addresses"}}, {"model": "translator.model_language_en", "pk": 60, "fields": {"value": "My shopping"}}, {"model": "translator.model_language_en", "pk": 61, "fields": {"value": "Favorite products"}}, {"model": "translator.model_language_en", "pk": 62, "fields": {"value": "Shopping cart"}}, {"model": "translator.model_language_en", "pk": 63, "fields": {"value": "Doctor's number"}}, {"model": "translator.model_language_en", "pk": 64, "fields": {"value": "Product can have only one image. Choice one option: paste URL or select image from disk."}}, {"model": "translator.model_language_en", "pk": 65, "fields": {"value": "Please select image."}}, {"model": "translator.model_language_en", "pk": 66, "fields": {"value": "It's not an image."}}, {"model": "translator.model_language_en", "pk": 67, "fields": {"value": "It's not an image."}}, {"model": "translator.model_language_en", "pk": 69, "fields": {"value": "Unauthorized access"}}, {"model": "translator.model_language_en", "pk": 70, "fields": {"value": "The dialog is reserved for logged-in user's or root."}}, {"model": "translator.model_language_en", "pk": 71, "fields": {"value": "Title"}}, {"model": "translator.model_language_en", "pk": 72, "fields": {"value": "Your name"}}, {"model": "translator.model_language_en", "pk": 73, "fields": {"value": "Email"}}, {"model": "translator.model_language_en", "pk": 74, "fields": {"value": "Message"}}, {"model": "translator.model_language_en", "pk": 75, "fields": {"value": "Product"}}, {"model": "translator.model_language_en", "pk": 76, "fields": {"value": "Url"}}, {"model": "translator.model_language_en", "pk": 77, "fields": {"value": "Product"}}, {"model": "translator.model_language_en", "pk": 78, "fields": {"value": "Url"}}, {"model": "translator.model_language_en", "pk": 79, "fields": {"value": "Product"}}, {"model": "translator.model_language_en", "pk": 80, "fields": {"value": "Url"}}, {"model": "translator.model_language_en", "pk": 81, "fields": {"value": "Question about product availability"}}, {"model": "translator.model_language_en", "pk": 82, "fields": {"value": "Comment on the website"}}, {"model": "translator.model_language_en", "pk": 83, "fields": {"value": "Other questions"}}, {"model": "translator.model_language_en", "pk": 84, "fields": {"value": "Password"}}, {"model": "translator.model_language_en", "pk": 85, "fields": {"value": "Wrong password"}}, {"model": "translator.model_language_en", "pk": 86, "fields": {"value": "Edit email address"}}, {"model": "translator.model_language_en", "pk": 87, "fields": {"value": "Edit username"}}, {"model": "translator.model_language_en", "pk": 88, "fields": {"value": "Edit password"}}, {"model": "translator.model_language_en", "pk": 89, "fields": {"value": "New email address"}}, {"model": "translator.model_language_en", "pk": 90, "fields": {"value": "New username"}}, {"model": "translator.model_language_en", "pk": 91, "fields": {"value": "New password"}}, {"model": "translator.model_language_en", "pk": 92, "fields": {"value": "First field is required"}}, {"model": "translator.model_language_en", "pk": 93, "fields": {"value": "Edit content"}}, {"model": "translator.model_language_en", "pk": 94, "fields": {"value": "The dialog is not valid in this URL address."}}, {"model": "translator.model_language_en", "pk": 95, "fields": {"value": "Header"}}, {"model": "translator.model_language_en", "pk": 96, "fields": {"value": "Paragraph"}}, {"model": "translator.model_language_en", "pk": 97, "fields": {"value": "Paste image URL"}}, {"model": "translator.model_language_en", "pk": 98, "fields": {"value": "Delete product"}}, {"model": "translator.model_language_en", "pk": 99, "fields": {"value": "Are you sure you want to remove the product?"}}, {"model": "translator.model_language_en", "pk": 100, "fields": {"value": "Clear cart"}}, {"model": "translator.model_language_en", "pk": 101, "fields": {"value": "Are you sure you want to clear cart?"}}, {"model": "translator.model_language_en", "pk": 102, "fields": {"value": "Sending..."}}, {"model": "translator.model_language_en", "pk": 103, "fields": {"value": "Waiting..."}}, {"model": "translator.model_language_en", "pk": 104, "fields": {"value": "It's done!"}}, {"model": "translator.model_language_en", "pk": 105, "fields": {"value": "Error / Resend"}}, {"model": "translator.model_language_en", "pk": 106, "fields": {"value": "invoice.pdf"}}, {"model": "translator.model_language_en", "pk": 107, "fields": {"value": "Delete address"}}, {"model": "translator.model_language_en", "pk": 108, "fields": {"value": "Are you sure you want to remove the address?"}}, {"model": "translator.model_language_en", "pk": 109, "fields": {"value": "Delete brand"}}, {"model": "translator.model_language_en", "pk": 110, "fields": {"value": "Are you sure you want to remove the brand? Number of products pinned to the brand {0}"}}, {"model": "translator.model_language_en", "pk": 111, "fields": {"value": "Delete purpose"}}, {"model": "translator.model_language_en", "pk": 112, "fields": {"value": "Are you sure you want to remove the purpose? Number of products pinned to the purpose {0}"}}, {"model": "translator.model_language_en", "pk": 113, "fields": {"value": "Arbuz"}}, {"model": "translator.model_language_en", "pk": 114, "fields": {"value": "Cart"}}, {"model": "translator.model_language_en", "pk": 115, "fields": {"value": "Dialog"}}, {"model": "translator.model_language_en", "pk": 116, "fields": {"value": "Main"}}, {"model": "translator.model_language_en", "pk": 117, "fields": {"value": "Navigation"}}, {"model": "translator.model_language_en", "pk": 118, "fields": {"value": "Payment"}}, {"model": "translator.model_language_en", "pk": 119, "fields": {"value": "Pdf"}}, {"model": "translator.model_language_en", "pk": 120, "fields": {"value": "Product"}}, {"model": "translator.model_language_en", "pk": 121, "fields": {"value": "Root"}}, {"model": "translator.model_language_en", "pk": 122, "fields": {"value": "Searcher"}}, {"model": "translator.model_language_en", "pk": 123, "fields": {"value": "Sender"}}, {"model": "translator.model_language_en", "pk": 124, "fields": {"value": "Session"}}, {"model": "translator.model_language_en", "pk": 125, "fields": {"value": "Setting"}}, {"model": "translator.model_language_en", "pk": 126, "fields": {"value": "Statement"}}, {"model": "translator.model_language_en", "pk": 127, "fields": {"value": "Translator"}}, {"model": "translator.model_language_en", "pk": 128, "fields": {"value": "User"}}, {"model": "translator.model_language_en", "pk": 129, "fields": {"value": "User Account"}}, {"model": "translator.model_language_en", "pk": 130, "fields": {"value": "invoice.pdf"}}, {"model": "translator.model_language_en", "pk": 131, "fields": {"value": "Show addresses"}}, {"model": "translator.model_language_en", "pk": 132, "fields": {"value": "Get invoice"}}, {"model": "translator.model_language_en", "pk": 133, "fields": {"value": "Close"}}, {"model": "translator.model_language_en", "pk": 134, "fields": {"value": "Clear filters"}}, {"model": "translator.model_language_en", "pk": 135, "fields": {"value": "Social media"}}, {"model": "translator.model_language_en", "pk": 136, "fields": {"value": "Delivery settings"}}, {"model": "translator.model_language_en", "pk": 137, "fields": {"value": "Credits"}}, {"model": "translator.model_language_en", "pk": 138, "fields": {"value": "Icons made by <a href=\"http://www.flaticon.com/authors/gregor-cresnar\" title=\"Gregor Cresnar\">Gregor Cresnar</a>, <a href=\"http://www.flaticon.com/authors/dave-gandy\" title=\"Dave Gandy\">Dave Gandy</a> and <a href=\"http://www.flaticon.com/authors/bogdan-rosu\" title=\"Bogdan Rosu\">Bogdan Rosu</a> <a href=\"http://www.freepik.com\" title=\"Freepik\">Freepik</a> from <a href=\"http://www.flaticon.com\" title=\"Flaticon\">www.flaticon.com</a> is licensed by <a href=\"http://creativecommons.org/licenses/by/3.0/\" title=\"Creative Commons BY 3.0\" target=\"_blank\">CC 3.0 BY</a>"}}, {"model": "translator.model_language_en", "pk": 139, "fields": {"value": "Phone"}}, {"model": "translator.model_language_en", "pk": 140, "fields": {"value": "Email"}}, {"model": "translator.model_language_en", "pk": 141, "fields": {"value": "Price in EUR"}}, {"model": "translator.model_language_en", "pk": 142, "fields": {"value": "Price in PLN"}}, {"model": "translator.model_language_en", "pk": 143, "fields": {"value": "Stock"}}, {"model": "translator.model_language_en", "pk": 144, "fields": {"value": "Name is required"}}, {"model": "translator.model_language_en", "pk": 145, "fields": {"value": "Modeling Mouth"}}, {"model": "translator.model_language_en", "pk": 146, "fields": {"value": "Deep Wrinkles"}}, {"model": "translator.model_language_en", "pk": 147, "fields": {"value": "Shallow Wrinkles"}}, {"model": "translator.model_language_en", "pk": 148, "fields": {"value": "Medium Wrinkles"}}, {"model": "translator.model_language_en", "pk": 149, "fields": {"value": "Volumetry"}}, {"model": "translator.model_language_en", "pk": 150, "fields": {"value": "Eye Area"}}, {"model": "translator.model_language_en", "pk": 151, "fields": {"value": "Payment was not successful"}}, {"model": "translator.model_language_en", "pk": 152, "fields": {"value": "Payments for selected products in Medifiller shop."}}, {"model": "translator.model_language_en", "pk": 153, "fields": {"value": "Delete paragraph"}}, {"model": "translator.model_language_en", "pk": 154, "fields": {"value": "Are you sure you want to remove the paragraph?"}}, {"model": "translator.model_language_en", "pk": 155, "fields": {"value": "The name is occupied"}}, {"model": "translator.model_language_en", "pk": 156, "fields": {"value": "Widget manager"}}, {"model": "translator.model_language_en", "pk": 157, "fields": {"value": "Catalog manager"}}, {"model": "translator.model_language_en", "pk": 158, "fields": {"value": "Product manager"}}, {"model": "translator.model_language_en", "pk": 159, "fields": {"value": "Product with the name exists"}}, {"model": "translator.model_language_en", "pk": 160, "fields": {"value": "Delete product description"}}, {"model": "translator.model_language_en", "pk": 161, "fields": {"value": "Are you sure you want to remove the description?"}}, {"model": "translator.model_language_en", "pk": 162, "fields": {"value": "Error"}}, {"model": "translator.model_language_en", "pk": 163, "fields": {"value": "Error"}}, {"model": "translator.model_language_en", "pk": 164, "fields": {"value": "Name"}}, {"model": "translator.model_language_en", "pk": 165, "fields": {"value": "Error - file name is required"}}, {"model": "translator.model_language_en", "pk": 166, "fields": {"value": "Error - image name is required"}}, {"model": "translator.model_language_en", "pk": 167, "fields": {"value": "Name"}}, {"model": "translator.model_language_en", "pk": 169, "fields": {"value": "Your note"}}, {"model": "translator.model_language_en", "pk": 170, "fields": {"value": "Deadline name"}}, {"model": "translator.model_language_en", "pk": 171, "fields": {"value": "Deadline settings"}}, {"model": "translator.model_language_en", "pk": 172, "fields": {"value": "Note settings"}}, {"model": "translator.model_language_en", "pk": 173, "fields": {"value": "Name"}}, {"model": "translator.model_language_en", "pk": 174, "fields": {"value": "Super price"}}, {"model": "translator.model_language_en", "pk": 175, "fields": {"value": "Name"}}, {"model": "translator.model_language_en", "pk": 176, "fields": {"value": "Name"}}, {"model": "translator.model_language_en", "pk": 177, "fields": {"value": "Copy element"}}, {"model": "translator.model_language_en", "pk": 178, "fields": {"value": " - copy"}}, {"model": "translator.model_language_en", "pk": 179, "fields": {"value": "Move element"}}, {"model": "translator.model_language_en", "pk": 180, "fields": {"value": "Check your CSRF token"}}, {"model": "translator.model_language_en", "pk": 181, "fields": {"value": "Forbidden"}}, {"model": "translator.model_language_en", "pk": 182, "fields": {"value": "Page Not Found"}}, {"model": "translator.model_language_en", "pk": 183, "fields": {"value": "Internal Server Error"}}, {"model": "translator.model_language_en", "pk": 184, "fields": {"value": "Price EUR"}}, {"model": "translator.model_language_en", "pk": 185, "fields": {"value": "Price PLN"}}, {"model": "translator.model_language_en", "pk": 186, "fields": {"value": "Price GBP"}}, {"model": "translator.model_language_en", "pk": 187, "fields": {"value": "Delete paragraph"}}, {"model": "translator.model_language_en", "pk": 188, "fields": {"value": "Are you sure you want to remove the paragraph?"}}, {"model": "translator.model_language_en", "pk": 189, "fields": {"value": "Select target catalog"}}, {"model": "translator.model_language_en", "pk": 190, "fields": {"value": "Title"}}, {"model": "translator.model_language_en", "pk": 191, "fields": {"value": "Message"}}, {"model": "translator.model_language_en", "pk": 192, "fields": {"value": "Send email"}}, {"model": "translator.model_language_en", "pk": 193, "fields": {"value": "We remind you about payment - deadline"}}, {"model": "translator.model_language_en", "pk": 194, "fields": {"value": "We remind you about payment - reminder"}}, {"model": "translator.model_language_en", "pk": 196, "fields": {"value": "Phone number"}}, {"model": "translator.model_language_en", "pk": 197, "fields": {"value": "Phone number"}}, {"model": "translator.model_language_en", "pk": 198, "fields": {"value": "Fax"}}, {"model": "translator.model_language_en", "pk": 199, "fields": {"value": "NIP / TIN"}}, {"model": "translator.model_language_en", "pk": 200, "fields": {"value": "Name"}}, {"model": "translator.model_language_en", "pk": 201, "fields": {"value": "Surname"}}, {"model": "translator.model_language_en", "pk": 202, "fields": {"value": "Company name"}}, {"model": "translator.model_language_en", "pk": 203, "fields": {"value": "Delete catalog"}}, {"model": "translator.model_language_en", "pk": 204, "fields": {"value": "Are you sure you want to remove the catalog?"}}, {"model": "translator.model_language_en", "pk": 205, "fields": {"value": "Payment settings"}}, {"model": "translator.model_language_en", "pk": 206, "fields": {"value": "The name is occupied in this catalog"}}, {"model": "translator.model_language_en", "pk": 207, "fields": {"value": "Loading..."}}, {"model": "translator.model_language_en", "pk": 208, "fields": {"value": "Empty"}}, {"model": "translator.model_language_en", "pk": 209, "fields": {"value": "Assign"}}, {"model": "translator.model_language_en", "pk": 210, "fields": {"value": "Pending"}}, {"model": "translator.model_language_en", "pk": 211, "fields": {"value": "Internal"}}, {"model": "translator.model_language_en", "pk": 212, "fields": {"value": "External"}}, {"model": "translator.model_language_en", "pk": 213, "fields": {"value": "Completed"}}, {"model": "translator.model_language_en", "pk": 214, "fields": {"value": "Deadline/Reminder"}}, {"model": "translator.model_language_en", "pk": 215, "fields": {"value": "Note"}}, {"model": "translator.model_language_en", "pk": 216, "fields": {"value": "Show addresses"}}, {"model": "translator.model_language_en", "pk": 217, "fields": {"value": "Send e-mail"}}, {"model": "translator.model_language_en", "pk": 218, "fields": {"value": "Get invoice"}}, {"model": "translator.model_language_en", "pk": 219, "fields": {"value": "No shopping found"}}, {"model": "translator.model_language_en", "pk": 220, "fields": {"value": "No payments found"}}, {"model": "translator.model_language_en", "pk": 221, "fields": {"value": "More"}}, {"model": "translator.model_language_en", "pk": 222, "fields": {"value": "Show more"}}, {"model": "translator.model_language_en", "pk": 223, "fields": {"value": "go back"}}, {"model": "translator.model_language_en", "pk": 224, "fields": {"value": "Prev page"}}, {"model": "translator.model_language_en", "pk": 225, "fields": {"value": "Next page"}}, {"model": "translator.model_language_en", "pk": 226, "fields": {"value": "Close"}}, {"model": "translator.model_language_en", "pk": 227, "fields": {"value": "Add element"}}, {"model": "translator.model_language_en", "pk": 228, "fields": {"value": "Before"}}, {"model": "translator.model_language_en", "pk": 229, "fields": {"value": "After"}}, {"model": "translator.model_language_en", "pk": 230, "fields": {"value": "Move"}}, {"model": "translator.model_language_en", "pk": 231, "fields": {"value": "Move up"}}, {"model": "translator.model_language_en", "pk": 232, "fields": {"value": "Move down"}}, {"model": "translator.model_language_en", "pk": 233, "fields": {"value": "Delete"}}, {"model": "translator.model_language_en", "pk": 234, "fields": {"value": "Copy"}}, {"model": "translator.model_language_en", "pk": 235, "fields": {"value": "Edit"}}, {"model": "translator.model_language_en", "pk": 236, "fields": {"value": "Create link"}}, {"model": "translator.model_language_en", "pk": 237, "fields": {"value": "Delete link"}}, {"model": "translator.model_language_en", "pk": 238, "fields": {"value": "Move link"}}, {"model": "translator.model_language_en", "pk": 239, "fields": {"value": "Copy link"}}, {"model": "translator.model_language_en", "pk": 240, "fields": {"value": "Add new catalog"}}, {"model": "translator.model_language_en", "pk": 241, "fields": {"value": "Add new product"}}, {"model": "translator.model_language_en", "pk": 242, "fields": {"value": "Clear filters"}}, {"model": "translator.model_language_en", "pk": 243, "fields": {"value": "EUR price"}}, {"model": "translator.model_language_en", "pk": 244, "fields": {"value": "PLN price"}}, {"model": "translator.model_language_en", "pk": 245, "fields": {"value": "GBP price"}}, {"model": "translator.model_language_en", "pk": 246, "fields": {"value": "Calculate"}}, {"model": "translator.model_language_en", "pk": 247, "fields": {"value": "Language"}}, {"model": "translator.model_language_en", "pk": 248, "fields": {"value": "Currency"}}, {"model": "translator.model_language_en", "pk": 249, "fields": {"value": "Home"}}, {"model": "translator.model_language_en", "pk": 250, "fields": {"value": "Products"}}, {"model": "translator.model_language_en", "pk": 251, "fields": {"value": "About"}}, {"model": "translator.model_language_en", "pk": 252, "fields": {"value": "Account"}}, {"model": "translator.model_language_en", "pk": 253, "fields": {"value": "Sign in"}}, {"model": "translator.model_language_en", "pk": 254, "fields": {"value": "Sign out"}}, {"model": "translator.model_language_en", "pk": 255, "fields": {"value": "Sign up"}}, {"model": "translator.model_language_en", "pk": 256, "fields": {"value": "Search"}}, {"model": "translator.model_language_en", "pk": 257, "fields": {"value": "Root settings"}}, {"model": "translator.model_language_en", "pk": 258, "fields": {"value": "Root sign out"}}, {"model": "translator.model_language_en", "pk": 259, "fields": {"value": "Notifications"}}, {"model": "translator.model_language_en", "pk": 260, "fields": {"value": "Contact"}}, {"model": "translator.model_language_en", "pk": 261, "fields": {"value": "Cart"}}, {"model": "translator.model_language_en", "pk": 262, "fields": {"value": "price to settle with the seller"}}, {"model": "translator.model_language_en", "pk": 263, "fields": {"value": "Courier"}}, {"model": "translator.model_language_en", "pk": 264, "fields": {"value": "Cash on delivery"}}, {"model": "translator.model_language_en", "pk": 265, "fields": {"value": "Personal receipt"}}, {"model": "translator.model_language_en", "pk": 266, "fields": {"value": "Data for public"}}, {"model": "translator.model_language_pl", "pk": 9, "fields": {"value": "Dodaj nowy polecany produkt"}}, {"model": "translator.model_language_pl", "pk": 10, "fields": {"value": "Aby dodać polecany produkt, należy wyszukać go w istniejących produktach na stronie. Następnie w szczegółach produktu nacisnąć na przycisk `Recommended`."}}, {"model": "translator.model_language_pl", "pk": 11, "fields": {"value": "Cena w walucie {0} musi być większa niż zero."}}, {"model": "translator.model_language_pl", "pk": 12, "fields": {"value": "Liczba produktów dostępnych w magazynie musi być większa niż zero."}}, {"model": "translator.model_language_pl", "pk": 15, "fields": {"value": "Producent produktu jest wymagany."}}, {"model": "translator.model_language_pl", "pk": 17, "fields": {"value": "Zdjęcie produktu jest wymagane."}}, {"model": "translator.model_language_pl", "pk": 18, "fields": {"value": "Słowa kluczowe"}}, {"model": "translator.model_language_pl", "pk": 19, "fields": {"value": "Nazwa"}}, {"model": "translator.model_language_pl", "pk": 20, "fields": {"value": "Opis"}}, {"model": "translator.model_language_pl", "pk": 23, "fields": {"value": "Zaloguj"}}, {"model": "translator.model_language_pl", "pk": 24, "fields": {"value": "Wyloguj"}}, {"model": "translator.model_language_pl", "pk": 25, "fields": {"value": "Dane firmy"}}, {"model": "translator.model_language_pl", "pk": 26, "fields": {"value": "Mapa adresów"}}, {"model": "translator.model_language_pl", "pk": 27, "fields": {"value": "Płatności użytkowników"}}, {"model": "translator.model_language_pl", "pk": 28, "fields": {"value": "Administrator nie istnieje."}}, {"model": "translator.model_language_pl", "pk": 29, "fields": {"value": "Błędne hasło."}}, {"model": "translator.model_language_pl", "pk": 30, "fields": {"value": "Błędne hasło. Spróbuj ponownie."}}, {"model": "translator.model_language_pl", "pk": 31, "fields": {"value": "Hasło"}}, {"model": "translator.model_language_pl", "pk": 32, "fields": {"value": "Zmień swoje hasło."}}, {"model": "translator.model_language_pl", "pk": 33, "fields": {"value": "Potwierdź swoje nowe konto."}}, {"model": "translator.model_language_pl", "pk": 34, "fields": {"value": "Twoje zamówienie zostało zatwierdzone."}}, {"model": "translator.model_language_pl", "pk": 35, "fields": {"value": "Zaloguj"}}, {"model": "translator.model_language_pl", "pk": 36, "fields": {"value": "Zarejestruj"}}, {"model": "translator.model_language_pl", "pk": 37, "fields": {"value": "Wyloguj"}}, {"model": "translator.model_language_pl", "pk": 38, "fields": {"value": "Konto"}}, {"model": "translator.model_language_pl", "pk": 39, "fields": {"value": "Email"}}, {"model": "translator.model_language_pl", "pk": 40, "fields": {"value": "Hasło"}}, {"model": "translator.model_language_pl", "pk": 41, "fields": {"value": "Użykownik z tym adresem email nie istnieje."}}, {"model": "translator.model_language_pl", "pk": 42, "fields": {"value": "Użytkownik z tym adresem email nie został potwierdzony. Sprawdź swoją skrzynkę mailową."}}, {"model": "translator.model_language_pl", "pk": 43, "fields": {"value": "Błędne hasło. Spróbuj ponownie."}}, {"model": "translator.model_language_pl", "pk": 44, "fields": {"value": "Nazwa użytkownika"}}, {"model": "translator.model_language_pl", "pk": 45, "fields": {"value": "Hasło"}}, {"model": "translator.model_language_pl", "pk": 46, "fields": {"value": "Email"}}, {"model": "translator.model_language_pl", "pk": 48, "fields": {"value": "Adres zamieszkania"}}, {"model": "translator.model_language_pl", "pk": 50, "fields": {"value": "Miasto"}}, {"model": "translator.model_language_pl", "pk": 51, "fields": {"value": "Stan / Prowincja / Region"}}, {"model": "translator.model_language_pl", "pk": 52, "fields": {"value": "ZIP / Kod pocztowy"}}, {"model": "translator.model_language_pl", "pk": 53, "fields": {"value": "Kraj"}}, {"model": "translator.model_language_pl", "pk": 54, "fields": {"value": "Użykownik z tym adresem email nie istnieje."}}, {"model": "translator.model_language_pl", "pk": 55, "fields": {"value": "Użytkownik z tym adresem email nie został potwierdzony. Sprawdź swoją skrzynkę mailową."}}, {"model": "translator.model_language_pl", "pk": 56, "fields": {"value": "Email"}}, {"model": "translator.model_language_pl", "pk": 57, "fields": {"value": "Hasło"}}, {"model": "translator.model_language_pl", "pk": 58, "fields": {"value": "Szczegóły konta"}}, {"model": "translator.model_language_pl", "pk": 59, "fields": {"value": "Adresy użytkownika"}}, {"model": "translator.model_language_pl", "pk": 60, "fields": {"value": "Moje zakupy"}}, {"model": "translator.model_language_pl", "pk": 61, "fields": {"value": "Ulubione produkty"}}, {"model": "translator.model_language_pl", "pk": 62, "fields": {"value": "Koszyk"}}, {"model": "translator.model_language_pl", "pk": 63, "fields": {"value": "Numer doktora"}}, {"model": "translator.model_language_pl", "pk": 64, "fields": {"value": "Produkt może posiadać tylko jedno zdjęcie. Może powinieneś usunąć adres URL?"}}, {"model": "translator.model_language_pl", "pk": 65, "fields": {"value": "Prosze wybrać zdjęcie."}}, {"model": "translator.model_language_pl", "pk": 66, "fields": {"value": "To nie jest zdjęcie."}}, {"model": "translator.model_language_pl", "pk": 67, "fields": {"value": "To nie jest zdjęcie."}}, {"model": "translator.model_language_pl", "pk": 69, "fields": {"value": "Nieautoryzowany dostęp"}}, {"model": "translator.model_language_pl", "pk": 70, "fields": {"value": "Ten komunikat jest zastrzeżony dla zalogowanych użytkowników lub administratora."}}, {"model": "translator.model_language_pl", "pk": 71, "fields": {"value": "Tytuł"}}, {"model": "translator.model_language_pl", "pk": 72, "fields": {"value": "Twoja godność"}}, {"model": "translator.model_language_pl", "pk": 73, "fields": {"value": "Email"}}, {"model": "translator.model_language_pl", "pk": 74, "fields": {"value": "Wiadomość"}}, {"model": "translator.model_language_pl", "pk": 75, "fields": {"value": "Produkt"}}, {"model": "translator.model_language_pl", "pk": 76, "fields": {"value": "Url"}}, {"model": "translator.model_language_pl", "pk": 77, "fields": {"value": "Produkt"}}, {"model": "translator.model_language_pl", "pk": 78, "fields": {"value": "Url"}}, {"model": "translator.model_language_pl", "pk": 79, "fields": {"value": "Produkt"}}, {"model": "translator.model_language_pl", "pk": 80, "fields": {"value": "Url"}}, {"model": "translator.model_language_pl", "pk": 81, "fields": {"value": "Pytanie o dostępność produktu"}}, {"model": "translator.model_language_pl", "pk": 82, "fields": {"value": "Uwagi dotyczące strony WWW"}}, {"model": "translator.model_language_pl", "pk": 83, "fields": {"value": "Inny temat"}}, {"model": "translator.model_language_pl", "pk": 84, "fields": {"value": "Hasło"}}, {"model": "translator.model_language_pl", "pk": 85, "fields": {"value": "Błędne hasło"}}, {"model": "translator.model_language_pl", "pk": 86, "fields": {"value": "Edycja adresu email"}}, {"model": "translator.model_language_pl", "pk": 87, "fields": {"value": "Edycja nazwy użytkownika"}}, {"model": "translator.model_language_pl", "pk": 88, "fields": {"value": "Edycja hasła użytkownika"}}, {"model": "translator.model_language_pl", "pk": 89, "fields": {"value": "Nowy adres email"}}, {"model": "translator.model_language_pl", "pk": 90, "fields": {"value": "Nowa nazwa użytkownika"}}, {"model": "translator.model_language_pl", "pk": 91, "fields": {"value": "Nowe hasło użytkownika"}}, {"model": "translator.model_language_pl", "pk": 92, "fields": {"value": "Pierwsze pole jest wymagane"}}, {"model": "translator.model_language_pl", "pk": 93, "fields": {"value": "Edycja zawartości zakładki"}}, {"model": "translator.model_language_pl", "pk": 94, "fields": {"value": "Te okno dialogowe musi zostać wykonane na prawidłowym adresie URL."}}, {"model": "translator.model_language_pl", "pk": 95, "fields": {"value": "Nagłówek"}}, {"model": "translator.model_language_pl", "pk": 96, "fields": {"value": "Akapit"}}, {"model": "translator.model_language_pl", "pk": 97, "fields": {"value": "Wklej adres URL obrazka"}}, {"model": "translator.model_language_pl", "pk": 98, "fields": {"value": "Usuwanie produktu"}}, {"model": "translator.model_language_pl", "pk": 99, "fields": {"value": "Jesteś pewny, że chcesz usunąć ten produkt?"}}, {"model": "translator.model_language_pl", "pk": 100, "fields": {"value": "Czyszczenie koszyka"}}, {"model": "translator.model_language_pl", "pk": 101, "fields": {"value": "Jesteś pewny, że chcesz wyczyścić koszyk?"}}, {"model": "translator.model_language_pl", "pk": 102, "fields": {"value": "Wysyłanie..."}}, {"model": "translator.model_language_pl", "pk": 103, "fields": {"value": "Oczekiwanie..."}}, {"model": "translator.model_language_pl", "pk": 104, "fields": {"value": "Zrobione!"}}, {"model": "translator.model_language_pl", "pk": 105, "fields": {"value": "Błąd / Ponów"}}, {"model": "translator.model_language_pl", "pk": 106, "fields": {"value": "faktura.pdf"}}, {"model": "translator.model_language_pl", "pk": 107, "fields": {"value": "Usuwanie adresu"}}, {"model": "translator.model_language_pl", "pk": 108, "fields": {"value": "Jesteś pewny, że chcesz usunąć ten adres?"}}, {"model": "translator.model_language_pl", "pk": 109, "fields": {"value": "Usuwanie producenta"}}, {"model": "translator.model_language_pl", "pk": 110, "fields": {"value": "Jesteś pewny, że chcesz usunąć tego producenta? Liczba produktów podpiętych pod tego producenta {0}"}}, {"model": "translator.model_language_pl", "pk": 111, "fields": {"value": "Usuwanie przeznaczenie produktu"}}, {"model": "translator.model_language_pl", "pk": 112, "fields": {"value": "Jesteś pewny, że chcesz usunąć te przeznaczenie produktu? Liczba produktów podpiętych pod tego przeznaczenia {0}"}}, {"model": "translator.model_language_pl", "pk": 113, "fields": {"value": "Arbuz"}}, {"model": "translator.model_language_pl", "pk": 114, "fields": {"value": "Koszyk"}}, {"model": "translator.model_language_pl", "pk": 115, "fields": {"value": "Dialog"}}, {"model": "translator.model_language_pl", "pk": 116, "fields": {"value": "Główna"}}, {"model": "translator.model_language_pl", "pk": 117, "fields": {"value": "Nawigacja"}}, {"model": "translator.model_language_pl", "pk": 118, "fields": {"value": "Płatności"}}, {"model": "translator.model_language_pl", "pk": 119, "fields": {"value": "Pdf"}}, {"model": "translator.model_language_pl", "pk": 120, "fields": {"value": "Produkt"}}, {"model": "translator.model_language_pl", "pk": 121, "fields": {"value": "Administrator"}}, {"model": "translator.model_language_pl", "pk": 122, "fields": {"value": "Wyszukiwarka"}}, {"model": "translator.model_language_pl", "pk": 123, "fields": {"value": "Nadawca"}}, {"model": "translator.model_language_pl", "pk": 124, "fields": {"value": "Sesja"}}, {"model": "translator.model_language_pl", "pk": 125, "fields": {"value": "Ustawienia"}}, {"model": "translator.model_language_pl", "pk": 126, "fields": {"value": "Komunikaty"}}, {"model": "translator.model_language_pl", "pk": 127, "fields": {"value": "Tłumacz"}}, {"model": "translator.model_language_pl", "pk": 128, "fields": {"value": "Użytkownik"}}, {"model": "translator.model_language_pl", "pk": 129, "fields": {"value": "Konto Użytkownika"}}, {"model": "translator.model_language_pl", "pk": 130, "fields": {"value": "faktura.pdf"}}, {"model": "translator.model_language_pl", "pk": 131, "fields": {"value": "Pokaż adresy"}}, {"model": "translator.model_language_pl", "pk": 132, "fields": {"value": "Pobierz fakturę"}}, {"model": "translator.model_language_pl", "pk": 133, "fields": {"value": "Zamknij"}}, {"model": "translator.model_language_pl", "pk": 134, "fields": {"value": "Wyczyść filtry"}}, {"model": "translator.model_language_pl", "pk": 135, "fields": {"value": "Media społecznościowe"}}, {"model": "translator.model_language_pl", "pk": 136, "fields": {"value": "Ustawienia dostawy"}}, {"model": "translator.model_language_pl", "pk": 137, "fields": {"value": "Kto stworzył ikony"}}, {"model": "translator.model_language_pl", "pk": 138, "fields": {"value": "Ikony zostały stworzone przez <a href=\"http://www.flaticon.com/authors/gregor-cresnar\" title=\"Gregor Cresnar\">Gregor Cresnar</a>, <a href=\"http://www.flaticon.com/authors/dave-gandy\" title=\"Dave Gandy\">Dave Gandy</a> i <a href=\"http://www.flaticon.com/authors/bogdan-rosu\" title=\"Bogdan Rosu\">Bogdan Rosu</a> <a href=\"http://www.freepik.com\" title=\"Freepik\">Freepik</a> z <a href=\"http://www.flaticon.com\" title=\"Flaticon\">www.flaticon.com</a> na licencji <a href=\"http://creativecommons.org/licenses/by/3.0/\" title=\"Creative Commons BY 3.0\" target=\"_blank\">CC 3.0 BY</a>"}}, {"model": "translator.model_language_pl", "pk": 139, "fields": {"value": "Telefon"}}, {"model": "translator.model_language_pl", "pk": 140, "fields": {"value": "Email"}}, {"model": "translator.model_language_pl", "pk": 141, "fields": {"value": "Cena w EUR"}}, {"model": "translator.model_language_pl", "pk": 142, "fields": {"value": "Cena w PLN"}}, {"model": "translator.model_language_pl", "pk": 143, "fields": {"value": "Magazyn"}}, {"model": "translator.model_language_pl", "pk": 144, "fields": {"value": "Nazwa jest wymagana"}}, {"model": "translator.model_language_pl", "pk": 145, "fields": {"value": "Modelowanie Ust"}}, {"model": "translator.model_language_pl", "pk": 146, "fields": {"value": "Zmarszczki Głębokie"}}, {"model": "translator.model_language_pl", "pk": 147, "fields": {"value": "Zmarszczki Płytkie"}}, {"model": "translator.model_language_pl", "pk": 148, "fields": {"value": "Zmarszczki Średnie"}}, {"model": "translator.model_language_pl", "pk": 149, "fields": {"value": "Wolumetria"}}, {"model": "translator.model_language_pl", "pk": 150, "fields": {"value": "Okolice Oczu"}}, {"model": "translator.model_language_pl", "pk": 151, "fields": {"value": "Płatność zakończona niepowodzeniem"}}, {"model": "translator.model_language_pl", "pk": 152, "fields": {"value": "Dokonywanie płatności za wybrane produkty w sklepie Medifiller."}}, {"model": "translator.model_language_pl", "pk": 153, "fields": {"value": "Usuń paragraf"}}, {"model": "translator.model_language_pl", "pk": 154, "fields": {"value": "Jesteś pewny, że chcesz usunąć ten paragraf?"}}, {"model": "translator.model_language_pl", "pk": 155, "fields": {"value": "Ta nazwa jest już zajęta"}}, {"model": "translator.model_language_pl", "pk": 156, "fields": {"value": "Zarządzanie widżetem"}}, {"model": "translator.model_language_pl", "pk": 157, "fields": {"value": "Zarządzanie katalogiem"}}, {"model": "translator.model_language_pl", "pk": 158, "fields": {"value": "Zarządzanie produktem"}}, {"model": "translator.model_language_pl", "pk": 159, "fields": {"value": "Produkt z tą nazwą już istnieje"}}, {"model": "translator.model_language_pl", "pk": 160, "fields": {"value": "Usuń opis produktu"}}, {"model": "translator.model_language_pl", "pk": 161, "fields": {"value": "Jesteś pewny, że chcesz usunąć ten opis?"}}, {"model": "translator.model_language_pl", "pk": 162, "fields": {"value": "Błąd"}}, {"model": "translator.model_language_pl", "pk": 163, "fields": {"value": "Błąd"}}, {"model": "translator.model_language_pl", "pk": 164, "fields": {"value": "Nazwa"}}, {"model": "translator.model_language_pl", "pk": 165, "fields": {"value": "Błąd - nazwa pliku jest wymagana"}}, {"model": "translator.model_language_pl", "pk": 166, "fields": {"value": "Błąd - nazwa obrazka jest wymagana"}}, {"model": "translator.model_language_pl", "pk": 167, "fields": {"value": "Nazwa"}}, {"model": "translator.model_language_pl", "pk": 169, "fields": {"value": "Twój notes"}}, {"model": "translator.model_language_pl", "pk": 170, "fields": {"value": "Nazwa terminu"}}, {"model": "translator.model_language_pl", "pk": 171, "fields": {"value": "Ustawienia terminarza"}}, {"model": "translator.model_language_pl", "pk": 172, "fields": {"value": "Ustawienia notatki"}}, {"model": "translator.model_language_pl", "pk": 173, "fields": {"value": "Nazwa"}}, {"model": "translator.model_language_pl", "pk": 174, "fields": {"value": "Dodatkowa cena"}}, {"model": "translator.model_language_pl", "pk": 175, "fields": {"value": "Nazwa"}}, {"model": "translator.model_language_pl", "pk": 176, "fields": {"value": "Nazwa"}}, {"model": "translator.model_language_pl", "pk": 177, "fields": {"value": "Kopiuj element"}}, {"model": "translator.model_language_pl", "pk": 178, "fields": {"value": " - kopia"}}, {"model": "translator.model_language_pl", "pk": 179, "fields": {"value": "Przenieś element"}}, {"model": "translator.model_language_pl", "pk": 180, "fields": {"value": "Sprawdź swój CSRF token"}}, {"model": "translator.model_language_pl", "pk": 181, "fields": {"value": "Brak uprawnień"}}, {"model": "translator.model_language_pl", "pk": 182, "fields": {"value": "Strona nie została znaleziona"}}, {"model": "translator.model_language_pl", "pk": 183, "fields": {"value": "Wewnętrzny błąd serwera"}}, {"model": "translator.model_language_pl", "pk": 184, "fields": {"value": "Cena EUR"}}, {"model": "translator.model_language_pl", "pk": 185, "fields": {"value": "Cena PLN"}}, {"model": "translator.model_language_pl", "pk": 186, "fields": {"value": "Cena GBP"}}, {"model": "translator.model_language_pl", "pk": 187, "fields": {"value": "Usuń paragraf"}}, {"model": "translator.model_language_pl", "pk": 188, "fields": {"value": "Jesteś pewien, że chcesz usunąć ten paragraf?"}}, {"model": "translator.model_language_pl", "pk": 189, "fields": {"value": "Wybierz katalog docelowy"}}, {"model": "translator.model_language_pl", "pk": 190, "fields": {"value": "Tytuł"}}, {"model": "translator.model_language_pl", "pk": 191, "fields": {"value": "Wiadomość"}}, {"model": "translator.model_language_pl", "pk": 192, "fields": {"value": "Wyślij email"}}, {"model": "translator.model_language_pl", "pk": 193, "fields": {"value": "Przypominamy o płatności - deadline"}}, {"model": "translator.model_language_pl", "pk": 194, "fields": {"value": "Przypominamy o płatności - reminder"}}, {"model": "translator.model_language_pl", "pk": 196, "fields": {"value": "Numer telefonu"}}, {"model": "translator.model_language_pl", "pk": 197, "fields": {"value": "Numer telefonu"}}, {"model": "translator.model_language_pl", "pk": 198, "fields": {"value": "Fax"}}, {"model": "translator.model_language_pl", "pk": 199, "fields": {"value": "NIP / TIN"}}, {"model": "translator.model_language_pl", "pk": 200, "fields": {"value": "Name"}}, {"model": "translator.model_language_pl", "pk": 201, "fields": {"value": "Surname"}}, {"model": "translator.model_language_pl", "pk": 202, "fields": {"value": "Nazwa firmy"}}, {"model": "translator.model_language_pl", "pk": 203, "fields": {"value": "Usuwanie katalogu"}}, {"model": "translator.model_language_pl", "pk": 204, "fields": {"value": "Jesteś pewny, że chcesz usunąć ten catalog?"}}, {"model": "translator.model_language_pl", "pk": 205, "fields": {"value": "Ustawienia płatności"}}, {"model": "translator.model_language_pl", "pk": 206, "fields": {"value": "Ta nazwa jest zajęta w katalogu"}}, {"model": "translator.model_language_pl", "pk": 207, "fields": {"value": "Ładowanie..."}}, {"model": "translator.model_language_pl", "pk": 208, "fields": {"value": "Pusty"}}, {"model": "translator.model_language_pl", "pk": 209, "fields": {"value": "Oznacz"}}, {"model": "translator.model_language_pl", "pk": 210, "fields": {"value": "Oczekujące"}}, {"model": "translator.model_language_pl", "pk": 211, "fields": {"value": "Wewnętrzne"}}, {"model": "translator.model_language_pl", "pk": 212, "fields": {"value": "Zewnętrzne"}}, {"model": "translator.model_language_pl", "pk": 213, "fields": {"value": "Zakończone"}}, {"model": "translator.model_language_pl", "pk": 214, "fields": {"value": "Deadline/przypomnienie"}}, {"model": "translator.model_language_pl", "pk": 215, "fields": {"value": "Notatka"}}, {"model": "translator.model_language_pl", "pk": 216, "fields": {"value": "Pokaż adresy"}}, {"model": "translator.model_language_pl", "pk": 217, "fields": {"value": "Wyślij e-mail"}}, {"model": "translator.model_language_pl", "pk": 218, "fields": {"value": "Pobierz fakturę"}}, {"model": "translator.model_language_pl", "pk": 219, "fields": {"value": "Nie znaleziono zakupów"}}, {"model": "translator.model_language_pl", "pk": 220, "fields": {"value": "Nie znaleziono płatności"}}, {"model": "translator.model_language_pl", "pk": 221, "fields": {"value": "Więcej"}}, {"model": "translator.model_language_pl", "pk": 222, "fields": {"value": "Pokaż więcej"}}, {"model": "translator.model_language_pl", "pk": 223, "fields": {"value": "wróć"}}, {"model": "translator.model_language_pl", "pk": 224, "fields": {"value": "Poprzednia"}}, {"model": "translator.model_language_pl", "pk": 225, "fields": {"value": "Następna"}}, {"model": "translator.model_language_pl", "pk": 226, "fields": {"value": "Zamknij"}}, {"model": "translator.model_language_pl", "pk": 227, "fields": {"value": "Dodaj element"}}, {"model": "translator.model_language_pl", "pk": 228, "fields": {"value": "Przed"}}, {"model": "translator.model_language_pl", "pk": 229, "fields": {"value": "Po"}}, {"model": "translator.model_language_pl", "pk": 230, "fields": {"value": "Przenieś"}}, {"model": "translator.model_language_pl", "pk": 231, "fields": {"value": "Przenieś do góry"}}, {"model": "translator.model_language_pl", "pk": 232, "fields": {"value": "Przenieś w dół"}}, {"model": "translator.model_language_pl", "pk": 233, "fields": {"value": "Usuń"}}, {"model": "translator.model_language_pl", "pk": 234, "fields": {"value": "Kopiuj"}}, {"model": "translator.model_language_pl", "pk": 235, "fields": {"value": "Edytuj"}}, {"model": "translator.model_language_pl", "pk": 236, "fields": {"value": "Stwórz link"}}, {"model": "translator.model_language_pl", "pk": 237, "fields": {"value": "Usuń link"}}, {"model": "translator.model_language_pl", "pk": 238, "fields": {"value": "Przenieś link"}}, {"model": "translator.model_language_pl", "pk": 239, "fields": {"value": "Kopiuj link"}}, {"model": "translator.model_language_pl", "pk": 240, "fields": {"value": "Dodaj nowy katalog"}}, {"model": "translator.model_language_pl", "pk": 241, "fields": {"value": "Dodaj nowy produkt"}}, {"model": "translator.model_language_pl", "pk": 242, "fields": {"value": "Wyczyść filtry"}}, {"model": "translator.model_language_pl", "pk": 243, "fields": {"value": "Cena EUR"}}, {"model": "translator.model_language_pl", "pk": 244, "fields": {"value": "Cena PLN"}}, {"model": "translator.model_language_pl", "pk": 245, "fields": {"value": "Cena GBP"}}, {"model": "translator.model_language_pl", "pk": 246, "fields": {"value": "Przelicz"}}, {"model": "translator.model_language_pl", "pk": 247, "fields": {"value": "Język"}}, {"model": "translator.model_language_pl", "pk": 248, "fields": {"value": "Waluta"}}, {"model": "translator.model_language_pl", "pk": 249, "fields": {"value": "Start"}}, {"model": "translator.model_language_pl", "pk": 250, "fields": {"value": "Produkty"}}, {"model": "translator.model_language_pl", "pk": 251, "fields": {"value": "O nas"}}, {"model": "translator.model_language_pl", "pk": 252, "fields": {"value": "Konto"}}, {"model": "translator.model_language_pl", "pk": 253, "fields": {"value": "Zaloguj"}}, {"model": "translator.model_language_pl", "pk": 254, "fields": {"value": "Wyloguj"}}, {"model": "translator.model_language_pl", "pk": 255, "fields": {"value": "Zarejestruj"}}, {"model": "translator.model_language_pl", "pk": 256, "fields": {"value": "Wyszukaj"}}, {"model": "translator.model_language_pl", "pk": 257, "fields": {"value": "Ustawienia administratora"}}, {"model": "translator.model_language_pl", "pk": 258, "fields": {"value": "Wyloguj"}}, {"model": "translator.model_language_pl", "pk": 259, "fields": {"value": "Powiadomienia"}}, {"model": "translator.model_language_pl", "pk": 260, "fields": {"value": "Kontakt"}}, {"model": "translator.model_language_pl", "pk": 261, "fields": {"value": "Koszyk"}}, {"model": "translator.model_language_pl", "pk": 262, "fields": {"value": "cena do ustalenia ze sprzedawcą"}}, {"model": "translator.model_language_pl", "pk": 263, "fields": {"value": "Kurier"}}, {"model": "translator.model_language_pl", "pk": 264, "fields": {"value": "Za pobraniem"}}, {"model": "translator.model_language_pl", "pk": 265, "fields": {"value": "Odbiór osobisty"}}, {"model": "translator.model_language_pl", "pk": 266, "fields": {"value": "Dane publiczne"}}]