[{"model": "product.catalog", "pk": 1, "fields": {"url_name": "first", "name": "First", "image": "", "parent": null}}, {"model": "product.catalog", "pk": 2, "fields": {"url_name": "second", "name": "Second", "image": "", "parent": null}}, {"model": "product.catalog", "pk": 3, "fields": {"url_name": "third", "name": "Third", "image": "", "parent": null}}, {"model": "product.catalog", "pk": 4, "fields": {"url_name": "first", "name": "First", "image": "", "parent": 1}}, {"model": "product.catalog", "pk": 5, "fields": {"url_name": "second", "name": "Second", "image": "", "parent": 1}}, {"model": "product.catalog", "pk": 6, "fields": {"url_name": "last", "name": "Last", "image": "", "parent": 4}}]